crawlect/__init__.py
crawlect/__main__.py
crawlect/cli.py
crawlect/cli_option_schema.py
crawlect/crawlect.py
crawlect/format.py
crawlect/languages.json
crawlect/llm.py
crawlect/llm_api_loader.py
crawlect/llm_code_analysis.py
crawlect/ollama_request.py
crawlect/openai_request.py
crawlect/output.py
crawlect/scan.py
crawlect-1.0.6.dist-info/licenses/LICENSE
crawlect-1.0.6.dist-info/METADATA
crawlect-1.0.6.dist-info/WHEEL
crawlect-1.0.6.dist-info/entry_points.txt
crawlect-1.0.6.dist-info/top_level.txt
crawlect-1.0.6.dist-info/RECORD
