Metadata-Version: 2.4
Name: Crawlect
Version: 1.0.6
Summary: Crawl, collect & document your codebase in Markdown — now with integrated LLM analysis.
Author-email: Yves Guillo & Alexandre Jenzer <yves@yvesguillo.ch>
License-Expression: MIT
Project-URL: Homepage, https://github.com/yvesguillo/crawlect
Project-URL: Issues, https://github.com/yvesguillo/crawlect/issues
Keywords: code crawler,documentation,markdown,LLM,static analysis
Classifier: Programming Language :: Python :: 3
Classifier: Operating System :: OS Independent
Classifier: Intended Audience :: Developers
Classifier: Topic :: Software Development :: Documentation
Requires-Python: >=3.10
License-File: LICENSE
Requires-Dist: gitignore_parser==0.1.12
Requires-Dist: openai==1.78.1
Requires-Dist: ollama==0.4.8
Dynamic: license-file
